<annotation>
  <folder>jinnan_dataset</folder>
  <filename>000915.jpg</filename>
  <size>
    <width>517</width>
    <height>335</height>
    <depth>3</depth>
  </size>
  <object>
    <name>3</name>
    <difficult>0</difficult>
    <bndbox>
      <xmin>274</xmin>
      <ymin>51</ymin>
      <xmax>335</xmax>
      <ymax>150</ymax>
    </bndbox>
  </object>
  <object>
    <name>2</name>
    <difficult>0</difficult>
    <bndbox>
      <xmin>141</xmin>
      <ymin>134</ymin>
      <xmax>188</xmax>
      <ymax>165</ymax>
    </bndbox>
  </object>
  <object>
    <name>2</name>
    <difficult>0</difficult>
    <bndbox>
      <xmin>212</xmin>
      <ymin>145</ymin>
      <xmax>265</xmax>
      <ymax>159</ymax>
    </bndbox>
  </object>
  <object>
    <name>2</name>
    <difficult>0</difficult>
    <bndbox>
      <xmin>244</xmin>
      <ymin>148</ymin>
      <xmax>283</xmax>
      <ymax>205</ymax>
    </bndbox>
  </object>
  <object>
    <name>2</name>
    <difficult>0</difficult>
    <bndbox>
      <xmin>158</xmin>
      <ymin>162</ymin>
      <xmax>248</xmax>
      <ymax>177</ymax>
    </bndbox>
  </object>
  <object>
    <name>2</name>
    <difficult>0</difficult>
    <bndbox>
      <xmin>161</xmin>
      <ymin>124</ymin>
      <xmax>220</xmax>
      <ymax>162</ymax>
    </bndbox>
  </object>
  <object>
    <name>2</name>
    <difficult>0</difficult>
    <bndbox>
      <xmin>176</xmin>
      <ymin>130</ymin>
      <xmax>240</xmax>
      <ymax>168</ymax>
    </bndbox>
  </object>
</annotation>
